acfunsdk_ws/__init__.py
acfunsdk_ws/acim.py
acfunsdk_ws/aclive.py
acfunsdk_ws/acws.py
acfunsdk_ws/blackboxprotobuf/__init__.py
acfunsdk_ws/blackboxprotobuf/libs/__init__.py
acfunsdk_ws/blackboxprotobuf/libs/interface.py
acfunsdk_ws/blackboxprotobuf/libs/types/__init__.py
acfunsdk_ws/blackboxprotobuf/libs/types/fixed.py
acfunsdk_ws/blackboxprotobuf/libs/types/length_delim.py
acfunsdk_ws/blackboxprotobuf/libs/types/type_maps.py
acfunsdk_ws/blackboxprotobuf/libs/types/varint.py
acfunsdk_ws/generate.bat
acfunsdk_ws/models/__init__.py
acfunsdk_ws/models/Im/__init__.py
acfunsdk_ws/models/Im/AcceptVoiceCallRequest_pb2.py
acfunsdk_ws/models/Im/AcceptVoiceCallResponse_pb2.py
acfunsdk_ws/models/Im/AccessPoint_pb2.py
acfunsdk_ws/models/Im/AccessPointsConfig_pb2.py
acfunsdk_ws/models/Im/AccountType_pb2.py
acfunsdk_ws/models/Im/AllUnreadCountRequest_pb2.py
acfunsdk_ws/models/Im/AllUnreadCountResponse_pb2.py
acfunsdk_ws/models/Im/AppInfo_pb2.py
acfunsdk_ws/models/Im/Attachment_pb2.py
acfunsdk_ws/models/Im/Attachments_pb2.py
acfunsdk_ws/models/Im/Audio_pb2.py
acfunsdk_ws/models/Im/AudioAttachment_pb2.py
acfunsdk_ws/models/Im/B2CMerchantSessionFolderCheckEvent_pb2.py
acfunsdk_ws/models/Im/B2CMerchantSessionFolderEvent_pb2.py
acfunsdk_ws/models/Im/B2CMessageBatchSendRequest_pb2.py
acfunsdk_ws/models/Im/B2CMessageBatchSendResponse_pb2.py
acfunsdk_ws/models/Im/B2CMessageDeleteRequest_pb2.py
acfunsdk_ws/models/Im/B2CMessageDeleteResponse_pb2.py
acfunsdk_ws/models/Im/B2CMessageReadAllRequest_pb2.py
acfunsdk_ws/models/Im/B2CMessageReadAllResponse_pb2.py
acfunsdk_ws/models/Im/B2CMessageReadRequest_pb2.py
acfunsdk_ws/models/Im/B2CMessageReadResponse_pb2.py
acfunsdk_ws/models/Im/B2CMessageRecallRequest_pb2.py
acfunsdk_ws/models/Im/B2CMessageRecallResponse_pb2.py
acfunsdk_ws/models/Im/B2CMessageReceiptCountGetRequest_pb2.py
acfunsdk_ws/models/Im/B2CMessageReceiptCountGetResponse_pb2.py
acfunsdk_ws/models/Im/B2CMessageReceiptDetailGetRequest_pb2.py
acfunsdk_ws-0.1.4.dist-info/LICENSE
acfunsdk_ws-0.1.4.dist-info/WHEEL
acfunsdk_ws-0.1.4.dist-info/METADATA
acfunsdk_ws-0.1.4.dist-info/RECORD
