Metadata-Version: 2.1
Name: acfunsdk-ws
Version: 0.1.4
Summary: acfunsdk - websocket
Home-page: https://pypi.org/project/acfunsdk-ws/
License: MIT
Keywords: acfun,sdk,acfunsdk,unofficeical,websocket
Author: dolacmeo
Author-email: dolacmeo@gmail.com
Requires-Python: >=3.8,<4.0
Classifier: Development Status :: 1 - Planning
Classifier: Environment :: Console
Classifier: Intended Audience :: Developers
Classifier: License :: OSI Approved :: MIT License
Classifier: Natural Language :: Chinese (Simplified)
Classifier: Natural Language :: English
Classifier: Operating System :: Microsoft :: Windows
Classifier: Operating System :: Microsoft :: Windows :: Windows 10
Classifier: Programming Language :: JavaScript
Classifier: Programming Language :: Python :: 3
Classifier: Programming Language :: Python :: 3.8
Classifier: Programming Language :: Python :: 3.9
Classifier: Programming Language :: Python :: 3.10
Classifier: Programming Language :: Python :: 3
Classifier: Programming Language :: Python :: 3.8
Classifier: Programming Language :: Python :: 3.9
Classifier: Topic :: Education
Classifier: Topic :: Internet :: WWW/HTTP :: Browsers
Classifier: Topic :: Software Development :: Libraries
Requires-Dist: acfunsdk (>=0.9.7,<0.10.0)
Requires-Dist: filetype (>=1.1,<2.0)
Requires-Dist: proto-plus (==1.22.1)
Requires-Dist: protobuf (==3.20.1)
Requires-Dist: pycryptodome (>=3.15,<4.0)
Requires-Dist: websocket-client (>=1.4,<2.0)
Project-URL: Bug Tracker, https://github.com/dolaCmeo/acfunsdk-ws/issues
Project-URL: Documentation, https://github.com/dolaCmeo/acfunsdk-ws
Project-URL: Repository, https://github.com/dolaCmeo/acfunsdk-ws
